LICENSE.txt
README.md
setup.py
rweb_datatable/__init__.py
rweb_datatable/html.py
rweb_datatable/models.py
rweb_datatable/utils.py
rweb_datatable.egg-info/PKG-INFO
rweb_datatable.egg-info/SOURCES.txt
rweb_datatable.egg-info/dependency_links.txt
rweb_datatable.egg-info/top_level.txt
rweb_datatable/renderers/__init__.py
rweb_datatable/renderers/csv.py
rweb_datatable/renderers/htmx.py